setup.py
algpros30/__init__.py
algpros30.egg-info/PKG-INFO
algpros30.egg-info/SOURCES.txt
algpros30.egg-info/dependency_links.txt
algpros30.egg-info/top_level.txt